{"homebrew_version":"1.5.12-76-g0f4e22e","used_options":[],"unused_options":[],"built_as_bottle":true,"poured_from_bottle":true,"installed_as_dependency":false,"installed_on_request":true,"changed_files":["bin/erb","bin/gem","bin/irb","bin/rake","bin/rdoc","bin/ri","lib/ruby/gems/2.5.0/gems/rdoc-6.0.1/exe/rdoc","lib/ruby/gems/2.5.0/gems/rdoc-6.0.1/exe/ri","libexec/gembin/bundle","ChangeLog","INSTALL_RECEIPT.json","lib/pkgconfig/ruby-2.5.pc","lib/ruby/2.5.0/bundler/vendor/fileutils/lib/fileutils.rb","lib/ruby/2.5.0/fileutils.rb","lib/ruby/2.5.0/mkmf.rb","lib/ruby/2.5.0/pathname.rb","lib/ruby/2.5.0/rubygems/basic_specification.rb","lib/ruby/2.5.0/rubygems/installer.rb","lib/ruby/2.5.0/rubygems/specification.rb","lib/ruby/2.5.0/shell.rb","lib/ruby/2.5.0/x86_64-darwin17/rbconfig.rb","share/man/man1/ruby.1"],"time":1533850651,"source_modified_time":1522255633,"HEAD":null,"stdlib":null,"compiler":"clang","aliases":["ruby@2.5"],"runtime_dependencies":[{"full_name":"libyaml","version":"0.2.1"},{"full_name":"openssl","version":"1.0.2o"},{"full_name":"readline","version":"7.0.5"}],"source":{"path":"/usr/local/Homebrew/Library/Taps/homebrew/homebrew-core/Formula/ruby.rb","tap":"homebrew/core","spec":"stable","versions":{"stable":"2.5.1","devel":"2.6.0-preview1","head":"HEAD","version_scheme":0}}}